move_unmarker/__init__.py
move_unmarker/unmarker.py
move_unmarker-0.1.4.dist-info/entry_points.txt
move_unmarker-0.1.4.dist-info/LICENSE
move_unmarker-0.1.4.dist-info/METADATA
move_unmarker-0.1.4.dist-info/WHEEL
move_unmarker-0.1.4.dist-info/RECORD
