Metadata-Version: 2.1
Name: move-unmarker
Version: 0.1.4
Summary: CLI utility to remove PII watermarks from pdfs downloaded from Move USP/ESALQ
Home-page: https://github.com/joaofauvel/move-unmarker
License: GPL-3.0-or-later
Keywords: pdf,watermark,manipulation,cli,USP,ESALQ
Author: João Fauvel
Author-email: jmmfauvel@gmail.com
Requires-Python: >=3.8
Classifier: License :: OSI Approved :: GNU General Public License v3 or later (GPLv3+)
Classifier: Programming Language :: Python :: 3
Classifier: Programming Language :: Python :: 3.8
Classifier: Programming Language :: Python :: 3.9
Classifier: Programming Language :: Python :: 3.10
Classifier: Programming Language :: Python :: 3.11
Classifier: Programming Language :: Python :: 3.12
Requires-Dist: pymupdf (>=1.24.3,<2.0.0)
Project-URL: Repository, https://github.com/joaofauvel/move-unmarker
